{
  "marketing_stripe": {
    "text": "",
    "link": ""
  },
  "contacts_stripe": {
    "pages": [
      {
        "title": "Torne-se um revendedor",
        "link": "/pages/contato"
      },
      {
        "title": "Blog",
        "link": ""
      },
      {
        "title": "Contato",
        "link": "/pages/contato"
      },
      {
        "title": "Nossa história",
        "link": "https://www.lindenleaves.com.br/pagina/a-marca"
      }
    ],
    "phone_wpp": false,
    "socials": true
  },
  "categories_list": {
    "featured": [],
    "random": 6,
    "full_width": true
  },
  "search_input": true
}